bmb_martlet_organization_client/__init__.py
bmb_martlet_organization_client/api_client.py
bmb_martlet_organization_client/configuration.py
bmb_martlet_organization_client/rest.py
bmb_martlet_organization_client/api/__init__.py
bmb_martlet_organization_client/api/addresses_api.py
bmb_martlet_organization_client/api/organizations_api.py
bmb_martlet_organization_client/api/system_api.py
bmb_martlet_organization_client/api/users_api.py
bmb_martlet_organization_client/models/__init__.py
bmb_martlet_organization_client/models/acceptance.py
bmb_martlet_organization_client/models/acceptance_response.py
bmb_martlet_organization_client/models/acceptances_response.py
bmb_martlet_organization_client/models/access_key.py
bmb_martlet_organization_client/models/access_key_response.py
bmb_martlet_organization_client/models/access_keys_response.py
bmb_martlet_organization_client/models/access_list.py
bmb_martlet_organization_client/models/access_list_activation.py
bmb_martlet_organization_client/models/access_list_activation_response.py
bmb_martlet_organization_client/models/access_list_deactivation_response.py
bmb_martlet_organization_client/models/access_list_entries_response.py
bmb_martlet_organization_client/models/access_list_entry.py
bmb_martlet_organization_client/models/access_list_entry_response.py
bmb_martlet_organization_client/models/access_list_response.py
bmb_martlet_organization_client/models/access_lists_response.py
bmb_martlet_organization_client/models/address.py
bmb_martlet_organization_client/models/address_profile.py
bmb_martlet_organization_client/models/address_profile_response.py
bmb_martlet_organization_client/models/address_profiles_request.py
bmb_martlet_organization_client/models/address_profiles_response.py
bmb_martlet_organization_client/models/address_query.py
bmb_martlet_organization_client/models/address_response.py
bmb_martlet_organization_client/models/addresses_response.py
bmb_martlet_organization_client/models/allowance.py
bmb_martlet_organization_client-0.177.0.dist-info/METADATA
bmb_martlet_organization_client-0.177.0.dist-info/WHEEL
bmb_martlet_organization_client-0.177.0.dist-info/top_level.txt
bmb_martlet_organization_client-0.177.0.dist-info/RECORD
