Metadata-Version: 2.1
Name: bmb-martlet-organization-client
Version: 0.177.0
Summary: Martlet Organization API
Home-page: UNKNOWN
Author: UNKNOWN
Author-email: apiteam@bmbix.com
License: UNKNOWN
Keywords: Swagger,Martlet Organization API
Platform: UNKNOWN
Requires-Dist: certifi
Requires-Dist: python-dateutil
Requires-Dist: six (>=1.10)
Requires-Dist: urllib3 (>=1.15)
